discourtesy/__init__.py
discourtesy/application.py
discourtesy/command.py
discourtesy/component.py
discourtesy/dispatch.py
discourtesy/http.py
discourtesy/routes/__init__.py
discourtesy/routes/index.py
discourtesy/routes/interaction.py
discourtesy/utils/__init__.py
discourtesy/utils/format.py
discourtesy/utils/options.py
discourtesy/utils/response.py
discourtesy-0.4.0.dist-info/LICENSE
discourtesy-0.4.0.dist-info/WHEEL
discourtesy-0.4.0.dist-info/METADATA
discourtesy-0.4.0.dist-info/RECORD
