Metadata-Version: 2.1
Name: discourtesy
Version: 0.4.0
Summary: A minimal framework to handle Discord interactions.
Home-page: https://github.com/robinmahieu/discourtesy
License: MIT
Keywords: discord,discourtesy
Author: Robin Mahieu
Author-email: robin.mahieu@protonmail.com
Requires-Python: >=3.10,<4.0
Classifier: License :: OSI Approved :: MIT License
Classifier: Programming Language :: Python :: 3
Classifier: Programming Language :: Python :: 3.10
Requires-Dist: PyNaCl (>=1.5.0,<2.0.0)
Requires-Dist: httpx (>=0.22.0,<0.23.0)
Requires-Dist: loguru (>=0.6.0,<0.7.0)
Requires-Dist: starlette (>=0.19.1,<0.20.0)
Requires-Dist: uvicorn (>=0.17.6,<0.18.0)
Project-URL: Repository, https://github.com/robinmahieu/discourtesy
